{
  "basics": {
    "name": "James Rainey",
    "label": "Computer Vision Researcher",
    "image": "",
    "email": "james.rainey@newcastle.ac.uk",
    "phone": "",
    "url": "https://github.com/james-rainey",
    "summary": "Innovative and results-driven Computer Vision Researcher with extensive experience in developing advanced computer vision solutions.",
    "location": {
      "address": "",
      "postalCode": "",
      "city": "Stirling",
      "countryCode": "UK",
      "region": "Scotland"
    },
    "profiles": [
      {
        "network": "Twitter",
        "username": "AlbertEinstein",
        "url": "https://twitter.com/AlbertEinstein"
      }
    ]
  },
  "work": [
    {
      "name": "Falcon Foodservice Equipment/Newcastle University",
      "position": "KTP Research Associate",
      "startDate": "2023-12-10",
      "endDate": "present",
      "summary": "Developing INtelligent FOod Recognition and Monitoring system (INFORM).",
      "highlights": ["Advanced from early concept to functioning product.","Acquired Patent for INFORM.","Disseminated research via publications."]
    },
    {
      "name": "Newcastle University",
      "position": "Research Associate",
      "startDate": "2022-09-01",
      "endDate": "2023-07-01",
      "summary": "Worked on various research projects.",
      "highlights": ["Early development on INtelligent FOod Recognition and Monitoring system (INFORM).",
      "Created a blockchain-based framework for media authentication", "Developed a Neuromorphic Vision System using spiking neural networks"]
    },
    {
      "name": "Stirling University",
      "position": "Postdoc Research Fellow",
      "startDate": "2022-04-01",
      "endDate": "2022-08-01",
      "summary": "Initial development of an embedded AI system for food recognition."
    }
  ],

  "education": [
    {
      "institution": "Queen's University Belfast",
      "location": "Belfast, Northern Ireland",
      "url": "https://www.qub.ac.uk",
      "area": "Gait Recognition - Developed a method for gait recognition using 3D Markerless Motion Capture.",
      "studyType": "PhD",
      "startDate": "2016-10-01",
      "endDate": "2020-12-01"
    },
    {
      "institution": "Queen's University Belfast",
      "location": "Belfast, Northern Ireland",
      "url": "https://www.qub.ac.uk",
      "area": "Computer Science",
      "studyType": "Undergraduate",
      "startDate": "2013-09-01",
      "endDate": "2016-06-01"
    }

  ],
  "skills": [
    {
      "name": "Programming",
      "icon": "fa-solid fa-hashtag",
      "keywords": [
        "Python",
        "C++",
        "JavaScript"
      ]
    },
    {
      "name": "Computer Vision",
      "icon": "fa-solid fa-hashtag",
      "keywords": [
        "Pytorch",
        "Tensorflow",
        "OpenCV",
        "PIL"
      ]
    },
    {
      "name": "Software Tools",
      "icon": "fa-solid fa-hashtag",
      "keywords": [
        "Git",
        "Vim",
        "AWS",
        "Latex"
      ]
    },
    {
      "name": "Hardware Tools",
      "icon": "fa-solid fa-hashtag",
      "keywords": [
        "Raspberry Pi",
        "NVidia Jetson",
        "Various Cameras and Sensors",
        "3D Printers"
      ]
    }
  ]
}
